hungarian_algorithm/__init__.py
hungarian_algorithm/algorithm.py
hungarian_algorithm/tests/__init__.py
hungarian_algorithm/tests/test_algorithm.py
hungarian_algorithm/tests/test_graph.py
hungarian_algorithm-0.1.11.dist-info/LICENSE
hungarian_algorithm-0.1.11.dist-info/METADATA
hungarian_algorithm-0.1.11.dist-info/WHEEL
hungarian_algorithm-0.1.11.dist-info/top_level.txt
hungarian_algorithm-0.1.11.dist-info/RECORD
