Metadata-Version: 2.1
Name: hungarian-algorithm
Version: 0.1.11
Summary: Python 3 implementation of the Hungarian Algorithm for the assignment problem.
Home-page: https://github.com/benchaplin/hungarian-algorithm
Author: Ben Chaplin
Author-email: benchaplin@protonmail.ch
License: UNKNOWN
Platform: UNKNOWN
Classifier: Programming Language :: Python :: 3
Classifier: License :: OSI Approved :: MIT License
Classifier: Operating System :: OS Independent
